accbib/__init__.py
accbib/accbib.py
accbib/iobib.py
accbib/ioxml.py
accbib/translator.py
accbib/version.py
accbib/data/JourList.json
accbib/data/JourList_User.json
accbib/data/__init__.py
accbib/data/xsl_yarosh/README.txt
accbib/data/xsl_yarosh/__init__.py
accbib/data/xsl_yarosh/cmarkup.xsl
accbib/data/xsl_yarosh/entities.xsl
accbib/data/xsl_yarosh/glayout.xsl
accbib/data/xsl_yarosh/mmltex.xsl
accbib/data/xsl_yarosh/scripts.xsl
accbib/data/xsl_yarosh/tables.xsl
accbib/data/xsl_yarosh/tokens.xsl
accbib-0.0.3.dist-info/LICENSE
accbib-0.0.3.dist-info/METADATA
accbib-0.0.3.dist-info/WHEEL
accbib-0.0.3.dist-info/top_level.txt
accbib-0.0.3.dist-info/RECORD
