Metadata-Version: 2.1
Name: accbib
Version: 0.0.3
Summary: a package to deal with bibliography
Author: Shellwe Wang
Author-email: shellwe.wang@gmail.com
Classifier: Programming Language :: Python :: 3
Classifier: License :: OSI Approved :: MIT License
Classifier: Operating System :: OS Independent
Requires-Python: >=3.6
License-File: LICENSE
